pyunittests.py
pyunittests-0.0.1.dist-info/LICENSE
pyunittests-0.0.1.dist-info/METADATA
pyunittests-0.0.1.dist-info/WHEEL
pyunittests-0.0.1.dist-info/top_level.txt
pyunittests-0.0.1.dist-info/RECORD
